easyocr/__init__.py
easyocr/cli.py
easyocr/config.py
easyocr/craft.py
easyocr/craft_utils.py
easyocr/detection.py
easyocr/detection_db.py
easyocr/easyocr.py
easyocr/export.py
easyocr/imgproc.py
easyocr/recognition.py
easyocr/utils.py
easyocr/DBNet/DBNet.py
easyocr/DBNet/README.md
easyocr/DBNet/assets/ops/dcn/__init__.py
easyocr/DBNet/assets/ops/dcn/setup.py
easyocr/DBNet/assets/ops/dcn/functions/__init__.py
easyocr/DBNet/assets/ops/dcn/functions/deform_conv.py
easyocr/DBNet/assets/ops/dcn/functions/deform_pool.py
easyocr/DBNet/assets/ops/dcn/modules/__init__.py
easyocr/DBNet/assets/ops/dcn/modules/deform_conv.py
easyocr/DBNet/assets/ops/dcn/modules/deform_pool.py
easyocr/DBNet/assets/ops/dcn/src/deform_conv_cpu.cpp
easyocr/DBNet/assets/ops/dcn/src/deform_conv_cpu_kernel.cpp
easyocr/DBNet/assets/ops/dcn/src/deform_conv_cpu_kernel.h
easyocr/DBNet/assets/ops/dcn/src/deform_conv_cuda.cpp
easyocr/DBNet/assets/ops/dcn/src/deform_conv_cuda_kernel.cu
easyocr/DBNet/assets/ops/dcn/src/deform_pool_cpu.cpp
easyocr/DBNet/assets/ops/dcn/src/deform_pool_cpu_kernel.cpp
easyocr/DBNet/assets/ops/dcn/src/deform_pool_cpu_kernel.h
easyocr/DBNet/assets/ops/dcn/src/deform_pool_cuda.cpp
easyocr/DBNet/assets/ops/dcn/src/deform_pool_cuda_kernel.cu
easyocr/DBNet/backbones/__init__.py
easyocr/DBNet/backbones/mobilenetv3.py
easyocr/DBNet/backbones/resnet.py
easyocr/DBNet/configs/DBNet_inference.yaml
easyocr/DBNet/decoders/__init__.py
easyocr/DBNet/decoders/balance_cross_entropy_loss.py
easyocr/DBNet/decoders/dice_loss.py
easyocr/DBNet/decoders/feature_attention.py
easyocr/DBNet/decoders/l1_loss.py
easyocr/DBNet/decoders/pss_loss.py
easyocr/DBNet/decoders/seg_detector.py
easyocr/DBNet/decoders/seg_detector_asf.py
easyocr/DBNet/decoders/seg_detector_loss.py
easyocr/DBNet/decoders/simple_detection.py
easyocr/DBNet/model/constructor.py
easyocr/DBNet/model/detector.py
easyocr/DBNet/model/model.py
easyocr/character/ab_char.txt
easyocr/character/abq_char.txt
easyocr/character/ady_char.txt
asoen_ocr-1.0.0.dist-info/LICENSE
asoen_ocr-1.0.0.dist-info/METADATA
asoen_ocr-1.0.0.dist-info/WHEEL
asoen_ocr-1.0.0.dist-info/top_level.txt
asoen_ocr-1.0.0.dist-info/RECORD
