Metadata-Version: 2.1
Name: asoen-ocr
Version: 1.0.0
Summary: End-to-End Multi-Lingual Optical Character Recognition (OCR) Solution
Home-page: UNKNOWN
Author: Muhammad Ramzan
Author-email: muhammad.ramzan@axcelerate.ai
License: Apache License 2.0
Keywords: ocr optical character recognition deep learning neural network
Platform: UNKNOWN
Classifier: Development Status :: 5 - Production/Stable
License-File: LICENSE
Requires-Dist: Pillow
Requires-Dist: PyYAML
Requires-Dist: Shapely
Requires-Dist: ninja
Requires-Dist: numpy
Requires-Dist: opencv-python
Requires-Dist: pyclipper
Requires-Dist: python-bidi
Requires-Dist: scikit-image
Requires-Dist: scipy
Requires-Dist: torch
Requires-Dist: torchvision (>=0.5)
